gmail_sender/__init__.py
gmail_sender/mail_sender_program.py
mail_sending_program-1.5.dist-info/LICENSE
mail_sending_program-1.5.dist-info/METADATA
mail_sending_program-1.5.dist-info/WHEEL
mail_sending_program-1.5.dist-info/top_level.txt
mail_sending_program-1.5.dist-info/RECORD
