Metadata-Version: 2.1
Name: mail-sending-program
Version: 1.5
Summary: a program that sends emails in one line
Home-page: https://pypi.org/project/mail-sending-program/
Author: py devoleper
Author-email: <mail.program.help@gmail.com>
License: MIT
Keywords: python,gmail,html,smtplib,auto,random
Classifier: Intended Audience :: Developers
Classifier: Programming Language :: Python :: 3
Classifier: Operating System :: MacOS :: MacOS X
Classifier: Operating System :: Microsoft :: Windows
Classifier: Development Status :: 4 - Beta
Classifier: Operating System :: POSIX :: Linux
License-File: LICENSE
